spidernets/__init__.py
spidernets/py.typed
spidernets-0.0.0.dist-info/METADATA
spidernets-0.0.0.dist-info/WHEEL
spidernets-0.0.0.dist-info/licenses/LICENSE
spidernets-0.0.0.dist-info/RECORD
