Metadata-Version: 2.4
Name: spidernets
Version: 0.0.0
Summary: Data structures for spider nets.
Project-URL: Repository, https://github.com/neverlocal/spidernets
Project-URL: Issues, https://github.com/neverlocal/spidernets/issues
Author: NeverLocal
License-Expression: LGPL-3.0
License-File: LICENSE
Classifier: Development Status :: 1 - Planning
Classifier: Natural Language :: English
Classifier: Operating System :: OS Independent
Classifier: Programming Language :: Python :: 3
Classifier: Programming Language :: Python :: 3.10
Classifier: Programming Language :: Python :: 3.11
Classifier: Programming Language :: Python :: 3.12
Classifier: Programming Language :: Python :: 3.13
Classifier: Typing :: Typed
Requires-Python: >=3.10
Requires-Dist: euler>=1.0.2.post0
Requires-Dist: numpy>=1.23
Requires-Dist: typing-validation>=1.2.12
